Week_2_System-on-Chip_and_BabySoC_Functional_Modelling/dac/avsddac.v

module avsddac( OUT, D, VREFH, VREFL);

  input VREFH;
  input VREFL;
  input [9:0] D;
  output OUT;

  wire real VSS, VDD, VREFL, VREFH;
  reg  real OUT;
  real NaN;
  wire EN;

  wire [10:0] Dext;	// unsigned extended

  assign Dext = {1'b0, D};
  assign EN = 1;
 
  
  initial begin
     NaN = 0.0 / 0.0;
     if (EN == 1'b0) begin
	OUT <= 0.0;
     end else if (VREFH == NaN) begin
	OUT <= NaN;
     end else if (VREFL == NaN) begin
	OUT <= NaN;
     end else if (EN == 1'b1) begin
	OUT <= VREFL + ($itor(Dext) / 1023.0) * (VREFH - VREFL);
     end else begin
	OUT <= NaN;
     end
  end

  always @(D or EN or VREFH or VREFL) begin
     if (EN == 1'b0) begin
	OUT <= 0.0;
     end else if (VREFH == NaN) begin
	OUT <= NaN;
     end else if (VREFL == NaN) begin
	OUT <= NaN;
     end else if (EN == 1'b1) begin
	OUT <= VREFL + ($itor(Dext) / 1023.0) * (VREFH - VREFL);
     end else begin
	OUT <= NaN;
     end
  end 

endmodule

Week_2_System-on-Chip_and_BabySoC_Functional_Modelling/dac/avsddac_tb_test.v
`timescale 1ns / 1ps

module avsddac_tb_test;
reg EN;
reg real VREFH, VREFL;
reg [9:0] D;
wire real OUT;

avsddac uut ( .OUT(OUT), .D(D), .VREFH(VREFH), .VREFL(VREFL) );

initial begin

   EN = 1'b0;
#5 EN = 1'b1;

end
initial begin
   VREFH = 3.3;
   VREFL = 0.0;
end

initial begin 

#10  D = 10'h3FA;
#10  D = 10'h3FB;
#10  D = 10'h3FC;
#10  D = 10'h3FD;
#10  D = 10'h3FE;
#10  D = 10'h3FF;


end

initial begin
        $dumpfile("avsddac_tb_test.vcd");
        $dumpvars(0,avsddac_tb_test);
        //clk = 1;
        //reset = 0;
        //#2 reset = 1;
	//#10 reset = 0;
        #300 $finish;
        end
        
endmodule

Week_2_System-on-Chip_and_BabySoC_Functional_Modelling/dac/avsddac_tb_test.vcd
$date
	Sun Oct  5 17:35:56 2025
$end
$version
	Icarus Verilog
$end
$timescale
	1ps
$end
$scope module avsddac_tb_test $end
$var reg 10 ! D [9:0] $end
$var reg 1 " EN $end
$var real 1 # VREFH $end
$var real 1 $ VREFL $end
$var real 1 % OUT $end
$scope module uut $end
$var wire 10 & D [9:0] $end
$var wire 1 ' EN $end
$var wire 11 ( Dext [10:0] $end
$var real 1 ) NaN $end
$var real 1 * OUT $end
$var real 1 + VREFH $end
$var real 1 , VREFL $end
$upscope $end
$upscope $end
$enddefinitions $end
#0
$dumpvars
r0 ,
r3.3 +
r0 *
rnan )
b0xxxxxxxxxx (
1'
bx &
r0 %
r0 $
r3.3 #
0"
bx !
$end
#5000
1"
#10000
r3.283870967741935 %
r3.283870967741935 *
b1111111010 (
b1111111010 !
b1111111010 &
#20000
r3.287096774193548 %
r3.287096774193548 *
b1111111011 (
b1111111011 !
b1111111011 &
#30000
r3.290322580645161 %
r3.290322580645161 *
b1111111100 (
b1111111100 !
b1111111100 &
#40000
r3.293548387096774 %
r3.293548387096774 *
b1111111101 (
b1111111101 !
b1111111101 &
#50000
r3.296774193548387 %
r3.296774193548387 *
b1111111110 (
b1111111110 !
b1111111110 &
#60000
r3.3 %
r3.3 *
b1111111111 (
b1111111111 !
b1111111111 &
