Week_2_System-on-Chip_and_BabySoC_Functional_Modelling/pll/avsdpll.v
`timescale 1ns / 1ps
module avsd_pll_1v8 (
    output reg CLK,
    input      VCO_IN,
    input      VDDA,
    input      VDDD,
    input      VSSA,
    input      VSSD,
    input      EN_VCO,
    input      REF
);
    real period, lastedge, refpd;

    initial begin
        lastedge = 0.0;
        period   = 25.0; // Default: 25ns period = 40 MHz
        CLK      = 1'b0;
    end

    // VCO clock generation loop
    always begin
        if (EN_VCO) begin
            #(period / 2.0) CLK = ~CLK;
        end else begin
            CLK = 1'b0;
            @(posedge EN_VCO); // Wait until re-enabled
        end
    end

    // Measure REF period and adjust VCO
    always @(posedge REF) begin
        if (lastedge > 0.0) begin
            refpd  = $realtime - lastedge;
            period = refpd / 8.0; // Target: 8× REF frequency
        end
        lastedge = $realtime;
    end
endmodule

Week_2_System-on-Chip_and_BabySoC_Functional_Modelling/pll/avsdpll_test.v
`timescale 1ns / 1ps
module avsdpll_tb;
    // Digital controls
    reg EN_VCO;
    reg REF;
    reg VCO_IN;

    // Power rails (kept as simple regs for simulation)
    reg VDDA, VDDD, VSSA, VSSD;

    wire CLK;

    avsd_pll_1v8 dut (
        .CLK(CLK),
        .VCO_IN(VCO_IN),
        .VDDA(VDDA),
        .VDDD(VDDD),
        .VSSA(VSSA),
        .VSSD(VSSD),
        .EN_VCO(EN_VCO),
        .REF(REF)
    );

    // Generate REF clock (e.g., 10 MHz = 100 ns period)
    initial begin
        REF = 0;
        forever #50 REF = ~REF; // 100 ns period
    end

    // Simulate VCO input signal
    initial begin
        VCO_IN = 0;
        forever #(83.33/2) VCO_IN = ~VCO_IN; // ~6 MHz example
    end

    initial begin
        VDDA = 1;  // tie to logic high
        VDDD = 1;
        VSSA = 0;
        VSSD = 0;

        EN_VCO = 0;
        #100 EN_VCO = 1;   // Enable VCO
        #2000 EN_VCO = 0;  // Disable for a while
        #200 EN_VCO = 1;   // Re-enable
        #2000 $finish;
    end

    initial begin
         $dumpfile("avsdpll_tb_test.vcd");
        $dumpvars(0,avsdpll_tb);
    end
endmodule

Week_2_System-on-Chip_and_BabySoC_Functional_Modelling/pll/avsdpll_tb_test.vcd
$date
	Sun Oct  5 17:59:42 2025
$end
$version
	Icarus Verilog
$end
$timescale
	1ps
$end
$scope module avsdpll_tb $end
$var wire 1 ! CLK $end
$var reg 1 " EN_VCO $end
$var reg 1 # REF $end
$var reg 1 $ VCO_IN $end
$var reg 1 % VDDA $end
$var reg 1 & VDDD $end
$var reg 1 ' VSSA $end
$var reg 1 ( VSSD $end
$scope module dut $end
$var wire 1 " EN_VCO $end
$var wire 1 # REF $end
$var wire 1 $ VCO_IN $end
$var wire 1 % VDDA $end
$var wire 1 & VDDD $end
$var wire 1 ' VSSA $end
$var wire 1 ( VSSD $end
$var reg 1 ! CLK $end
$var real 1 ) lastedge $end
$var real 1 * period $end
$var real 1 + refpd $end
$upscope $end
$upscope $end
$enddefinitions $end
#0
$dumpvars
r0 +
r25 *
r0 )
0(
0'
1&
1%
0$
0#
0"
0!
$end
#41665
1$
#50000
r50 )
1#
#83330
0$
#100000
0#
1"
#112500
1!
#124995
1$
#125000
0!
#137500
1!
#150000
r150 )
r12.5 *
r100 +
0!
1#
#162500
1!
#166660
0$
#168750
0!
#175000
1!
#181250
0!
#187500
1!
#193750
0!
#200000
1!
0#
#206250
0!
#208325
1$
#212500
1!
#218750
0!
#225000
1!
#231250
0!
#237500
1!
#243750
0!
#249990
0$
#250000
r250 )
1!
1#
#256250
0!
#262500
1!
#268750
0!
#275000
1!
#281250
0!
#287500
1!
#291655
1$
#293750
0!
#300000
1!
0#
#306250
0!
#312500
1!
#318750
0!
#325000
1!
#331250
0!
#333320
0$
#337500
1!
#343750
0!
#350000
r350 )
1!
1#
#356250
0!
#362500
1!
#368750
0!
#374985
1$
#375000
1!
#381250
0!
#387500
1!
#393750
0!
#400000
1!
0#
#406250
0!
#412500
1!
#416650
0$
#418750
0!
#425000
1!
#431250
0!
#437500
1!
#443750
0!
#450000
r450 )
1!
1#
#456250
0!
#458315
1$
#462500
1!
#468750
0!
#475000
1!
#481250
0!
#487500
1!
#493750
0!
#499980
0$
#500000
1!
0#
#506250
0!
#512500
1!
#518750
0!
#525000
1!
#531250
0!
#537500
1!
#541645
1$
#543750
0!
#550000
r550 )
1!
1#
#556250
0!
#562500
1!
#568750
0!
#575000
1!
#581250
0!
#583310
0$
#587500
1!
#593750
0!
#600000
1!
0#
#606250
0!
#612500
1!
#618750
0!
#624975
1$
#625000
1!
#631250
0!
#637500
1!
#643750
0!
#650000
r650 )
1!
1#
#656250
0!
#662500
1!
#666640
0$
#668750
0!
#675000
1!
#681250
0!
#687500
1!
#693750
0!
#700000
1!
0#
#706250
0!
#708305
1$
#712500
1!
#718750
0!
#725000
1!
#731250
0!
#737500
1!
#743750
0!
#749970
0$
#750000
r750 )
1!
1#
#756250
0!
#762500
1!
#768750
0!
#775000
1!
#781250
0!
#787500
1!
#791635
1$
#793750
0!
#800000
1!
0#
#806250
0!
#812500
1!
#818750
0!
#825000
1!
#831250
0!
#833300
0$
#837500
1!
#843750
0!
#850000
r850 )
1!
1#
#856250
0!
#862500
1!
#868750
0!
#874965
1$
#875000
1!
#881250
0!
#887500
1!
#893750
0!
#900000
1!
0#
#906250
0!
#912500
1!
#916630
0$
#918750
0!
#925000
1!
#931250
0!
#937500
1!
#943750
0!
#950000
r950 )
1!
1#
#956250
0!
#958295
1$
#962500
1!
#968750
0!
#975000
1!
#981250
0!
#987500
1!
#993750
0!
#999960
0$
#1000000
1!
0#
#1006250
0!
#1012500
1!
#1018750
0!
#1025000
1!
#1031250
0!
#1037500
1!
#1041625
1$
#1043750
0!
#1050000
r1050 )
1!
1#
#1056250
0!
#1062500
1!
#1068750
0!
#1075000
1!
#1081250
0!
#1083290
0$
#1087500
1!
#1093750
0!
#1100000
1!
0#
#1106250
0!
#1112500
1!
#1118750
0!
#1124955
1$
#1125000
1!
#1131250
0!
#1137500
1!
#1143750
0!
#1150000
r1150 )
1!
1#
#1156250
0!
#1162500
1!
#1166620
0$
#1168750
0!
#1175000
1!
#1181250
0!
#1187500
1!
#1193750
0!
#1200000
1!
0#
#1206250
0!
#1208285
1$
#1212500
1!
#1218750
0!
#1225000
1!
#1231250
0!
#1237500
1!
#1243750
0!
#1249950
0$
#1250000
r1250 )
1!
1#
#1256250
0!
#1262500
1!
#1268750
0!
#1275000
1!
#1281250
0!
#1287500
1!
#1291615
1$
#1293750
0!
#1300000
1!
0#
#1306250
0!
#1312500
1!
#1318750
0!
#1325000
1!
#1331250
0!
#1333280
0$
#1337500
1!
#1343750
0!
#1350000
r1350 )
1!
1#
#1356250
0!
#1362500
1!
#1368750
0!
#1374945
1$
#1375000
1!
#1381250
0!
#1387500
1!
#1393750
0!
#1400000
1!
0#
#1406250
0!
#1412500
1!
#1416610
0$
#1418750
0!
#1425000
1!
#1431250
0!
#1437500
1!
#1443750
0!
#1450000
r1450 )
1!
1#
#1456250
0!
#1458275
1$
#1462500
1!
#1468750
0!
#1475000
1!
#1481250
0!
#1487500
1!
#1493750
0!
#1499940
0$
#1500000
1!
0#
#1506250
0!
#1512500
1!
#1518750
0!
#1525000
1!
#1531250
0!
#1537500
1!
#1541605
1$
#1543750
0!
#1550000
r1550 )
1!
1#
#1556250
0!
#1562500
1!
#1568750
0!
#1575000
1!
#1581250
0!
#1583270
0$
#1587500
1!
#1593750
0!
#1600000
1!
0#
#1606250
0!
#1612500
1!
#1618750
0!
#1624935
1$
#1625000
1!
#1631250
0!
#1637500
1!
#1643750
0!
#1650000
r1650 )
1!
1#
#1656250
0!
#1662500
1!
#1666600
0$
#1668750
0!
#1675000
1!
#1681250
0!
#1687500
1!
#1693750
0!
#1700000
1!
0#
#1706250
0!
#1708265
1$
#1712500
1!
#1718750
0!
#1725000
1!
#1731250
0!
#1737500
1!
#1743750
0!
#1749930
0$
#1750000
r1750 )
1!
1#
#1756250
0!
#1762500
1!
#1768750
0!
#1775000
1!
#1781250
0!
#1787500
1!
#1791595
1$
#1793750
0!
#1800000
1!
0#
#1806250
0!
#1812500
1!
#1818750
0!
#1825000
1!
#1831250
0!
#1833260
0$
#1837500
1!
#1843750
0!
#1850000
r1850 )
1!
1#
#1856250
0!
#1862500
1!
#1868750
0!
#1874925
1$
#1875000
1!
#1881250
0!
#1887500
1!
#1893750
0!
#1900000
1!
0#
#1906250
0!
#1912500
1!
#1916590
0$
#1918750
0!
#1925000
1!
#1931250
0!
#1937500
1!
#1943750
0!
#1950000
r1950 )
1!
1#
#1956250
0!
#1958255
1$
#1962500
1!
#1968750
0!
#1975000
1!
#1981250
0!
#1987500
1!
#1993750
0!
#1999920
0$
#2000000
1!
0#
#2006250
0!
#2012500
1!
#2018750
0!
#2025000
1!
#2031250
0!
#2037500
1!
#2041585
1$
#2043750
0!
#2050000
r2050 )
1!
1#
#2056250
0!
#2062500
1!
#2068750
0!
#2075000
1!
#2081250
0!
#2083250
0$
#2087500
1!
#2093750
0!
#2100000
0!
0#
0"
#2124915
1$
#2150000
r2150 )
1#
#2166580
0$
#2200000
0#
#2208245
1$
#2249910
0$
#2250000
r2250 )
1#
#2291575
1$
#2300000
0#
1"
#2306250
1!
#2312500
0!
#2318750
1!
#2325000
0!
#2331250
1!
#2333240
0$
#2337500
0!
#2343750
1!
#2350000
r2350 )
0!
1#
#2356250
1!
#2362500
0!
#2368750
1!
#2374905
1$
#2375000
0!
#2381250
1!
#2387500
0!
#2393750
1!
#2400000
0!
0#
#2406250
1!
#2412500
0!
#2416570
0$
#2418750
1!
#2425000
0!
#2431250
1!
#2437500
0!
#2443750
1!
#2450000
r2450 )
0!
1#
#2456250
1!
#2458235
1$
#2462500
0!
#2468750
1!
#2475000
0!
#2481250
1!
#2487500
0!
#2493750
1!
#2499900
0$
#2500000
0!
0#
#2506250
1!
#2512500
0!
#2518750
1!
#2525000
0!
#2531250
1!
#2537500
0!
#2541565
1$
#2543750
1!
#2550000
r2550 )
0!
1#
#2556250
1!
#2562500
0!
#2568750
1!
#2575000
0!
#2581250
1!
#2583230
0$
#2587500
0!
#2593750
1!
#2600000
0!
0#
#2606250
1!
#2612500
0!
#2618750
1!
#2624895
1$
#2625000
0!
#2631250
1!
#2637500
0!
#2643750
1!
#2650000
r2650 )
0!
1#
#2656250
1!
#2662500
0!
#2666560
0$
#2668750
1!
#2675000
0!
#2681250
1!
#2687500
0!
#2693750
1!
#2700000
0!
0#
#2706250
1!
#2708225
1$
#2712500
0!
#2718750
1!
#2725000
0!
#2731250
1!
#2737500
0!
#2743750
1!
#2749890
0$
#2750000
r2750 )
0!
1#
#2756250
1!
#2762500
0!
#2768750
1!
#2775000
0!
#2781250
1!
#2787500
0!
#2791555
1$
#2793750
1!
#2800000
0!
0#
#2806250
1!
#2812500
0!
#2818750
1!
#2825000
0!
#2831250
1!
#2833220
0$
#2837500
0!
#2843750
1!
#2850000
r2850 )
0!
1#
#2856250
1!
#2862500
0!
#2868750
1!
#2874885
1$
#2875000
0!
#2881250
1!
#2887500
0!
#2893750
1!
#2900000
0!
0#
#2906250
1!
#2912500
0!
#2916550
0$
#2918750
1!
#2925000
0!
#2931250
1!
#2937500
0!
#2943750
1!
#2950000
r2950 )
0!
1#
#2956250
1!
#2958215
1$
#2962500
0!
#2968750
1!
#2975000
0!
#2981250
1!
#2987500
0!
#2993750
1!
#2999880
0$
#3000000
0!
0#
#3006250
1!
#3012500
0!
#3018750
1!
#3025000
0!
#3031250
1!
#3037500
0!
#3041545
1$
#3043750
1!
#3050000
r3050 )
0!
1#
#3056250
1!
#3062500
0!
#3068750
1!
#3075000
0!
#3081250
1!
#3083210
0$
#3087500
0!
#3093750
1!
#3100000
0!
0#
#3106250
1!
#3112500
0!
#3118750
1!
#3124875
1$
#3125000
0!
#3131250
1!
#3137500
0!
#3143750
1!
#3150000
r3150 )
0!
1#
#3156250
1!
#3162500
0!
#3166540
0$
#3168750
1!
#3175000
0!
#3181250
1!
#3187500
0!
#3193750
1!
#3200000
0!
0#
#3206250
1!
#3208205
1$
#3212500
0!
#3218750
1!
#3225000
0!
#3231250
1!
#3237500
0!
#3243750
1!
#3249870
0$
#3250000
r3250 )
0!
1#
#3256250
1!
#3262500
0!
#3268750
1!
#3275000
0!
#3281250
1!
#3287500
0!
#3291535
1$
#3293750
1!
#3300000
0!
0#
#3306250
1!
#3312500
0!
#3318750
1!
#3325000
0!
#3331250
1!
#3333200
0$
#3337500
0!
#3343750
1!
#3350000
r3350 )
0!
1#
#3356250
1!
#3362500
0!
#3368750
1!
#3374865
1$
#3375000
0!
#3381250
1!
#3387500
0!
#3393750
1!
#3400000
0!
0#
#3406250
1!
#3412500
0!
#3416530
0$
#3418750
1!
#3425000
0!
#3431250
1!
#3437500
0!
#3443750
1!
#3450000
r3450 )
0!
1#
#3456250
1!
#3458195
1$
#3462500
0!
#3468750
1!
#3475000
0!
#3481250
1!
#3487500
0!
#3493750
1!
#3499860
0$
#3500000
0!
0#
#3506250
1!
#3512500
0!
#3518750
1!
#3525000
0!
#3531250
1!
#3537500
0!
#3541525
1$
#3543750
1!
#3550000
r3550 )
0!
1#
#3556250
1!
#3562500
0!
#3568750
1!
#3575000
0!
#3581250
1!
#3583190
0$
#3587500
0!
#3593750
1!
#3600000
0!
0#
#3606250
1!
#3612500
0!
#3618750
1!
#3624855
1$
#3625000
0!
#3631250
1!
#3637500
0!
#3643750
1!
#3650000
r3650 )
0!
1#
#3656250
1!
#3662500
0!
#3666520
0$
#3668750
1!
#3675000
0!
#3681250
1!
#3687500
0!
#3693750
1!
#3700000
0!
0#
#3706250
1!
#3708185
1$
#3712500
0!
#3718750
1!
#3725000
0!
#3731250
1!
#3737500
0!
#3743750
1!
#3749850
0$
#3750000
r3750 )
0!
1#
#3756250
1!
#3762500
0!
#3768750
1!
#3775000
0!
#3781250
1!
#3787500
0!
#3791515
1$
#3793750
1!
#3800000
0!
0#
#3806250
1!
#3812500
0!
#3818750
1!
#3825000
0!
#3831250
1!
#3833180
0$
#3837500
0!
#3843750
1!
#3850000
r3850 )
0!
1#
#3856250
1!
#3862500
0!
#3868750
1!
#3874845
1$
#3875000
0!
#3881250
1!
#3887500
0!
#3893750
1!
#3900000
0!
0#
#3906250
1!
#3912500
0!
#3916510
0$
#3918750
1!
#3925000
0!
#3931250
1!
#3937500
0!
#3943750
1!
#3950000
r3950 )
0!
1#
#3956250
1!
#3958175
1$
#3962500
0!
#3968750
1!
#3975000
0!
#3981250
1!
#3987500
0!
#3993750
1!
#3999840
0$
#4000000
0!
0#
#4006250
1!
#4012500
0!
#4018750
1!
#4025000
0!
#4031250
1!
#4037500
0!
#4041505
1$
#4043750
1!
#4050000
r4050 )
0!
1#
#4056250
1!
#4062500
0!
#4068750
1!
#4075000
0!
#4081250
1!
#4083170
0$
#4087500
0!
#4093750
1!
#4100000
0!
0#
#4106250
1!
#4112500
0!
#4118750
1!
#4124835
1$
#4125000
0!
#4131250
1!
#4137500
0!
#4143750
1!
#4150000
r4150 )
0!
1#
#4156250
1!
#4162500
0!
#4166500
0$
#4168750
1!
#4175000
0!
#4181250
1!
#4187500
0!
#4193750
1!
#4200000
0!
0#
#4206250
1!
#4208165
1$
#4212500
0!
#4218750
1!
#4225000
0!
#4231250
1!
#4237500
0!
#4243750
1!
#4249830
0$
#4250000
r4250 )
0!
1#
#4256250
1!
#4262500
0!
#4268750
1!
#4275000
0!
#4281250
1!
#4287500
0!
#4291495
1$
#4293750
1!
#4300000
0!
0#
